[
    {
        "ime;naslov;kraj;lat;lng": "Splosna Bolnisnica Celje;Oblakova ulica 5;3000 Celje;46.23432;15.2644"
    },
    {
        "ime;naslov;kraj;lat;lng": "Bolnisnica Topolsica;Topolsica 61;3326 Topolsica;46.400998;15.020752"
    },
    {
        "ime;naslov;kraj;lat;lng": "Bolnisnica Postojna;Precna Ulica 4;6230 Postojna;45.771515;14.209992"
    },
    {
        "ime;naslov;kraj;lat;lng": "Bolnisnica Sezana;Cankarjeva Ulica 4;6210 Sezana;45.709305;13.867593"
    },
    {
        "ime;naslov;kraj;lat;lng": "Splosna Bolnisnica Izola;Polje 40;6310 Izola;45.544424;13.687097"
    },
    {
        "ime;naslov;kraj;lat;lng": "Splosna Bolnisnica Jesenice;Cesta Marsala Tita 112;4270 Jesenice;46.442996;14.036972"
    },
    {
        "ime;naslov;kraj;lat;lng": "Splosna Bolnisnica Brezice;Cernelceva Cesta 15;8250 Brezice;45.90849;15.593572"
    },
    {
        "ime;naslov;kraj;lat;lng": "Klinicni Center Ljubljana;Zaloska Cesta 2;1000 Ljubljana;46.052207;14.520775"
    },
    {
        "ime;naslov;kraj;lat;lng": "Splosna Bolnisnica Trbovlje;Rudarska Cesta 9;1420 Trbovlje;46.153986;15.047091"
    },
    {
        "ime;naslov;kraj;lat;lng": "Bolnisnica Ptuj;Potrceva Cesta 23;2250 Ptuj;46.426099;15.877099"
    },
    {
        "ime;naslov;kraj;lat;lng": "Splosna Bolnisnica Maribor;Ljubljanska Ulica 2;2000 Maribor;46.552881;15.648563"
    },
    {
        "ime;naslov;kraj;lat;lng": "Splosna Bolnisnica Murska Sobota;Ulica dr. Vrbnjaka 6;9000 Murska Sobota;46.65014;16.18729"
    },
    {
        "ime;naslov;kraj;lat;lng": "Splosna Bolnisnica dr. Franca Derganca;Ulica Padlih Borcev 13A;5290 Sempeter pri Gorici;45.930204;13.640835"
    },
    {
        "ime;naslov;kraj;lat;lng": "Splosna Bolnisnica Novo Mesto;Smihelska Cesta 1;8000 Novo Mesto;45.800163;15.163841"
    },
    {
        "ime;naslov;kraj;lat;lng": "Splosna Bolnisnica Slovenj Gradec;Gosposvetska Cesta 3;2380 Slovenj Gradec;46.507321;15.080068"
    }
]